hypnocube/__init__.py
hypnocube/cube_animator.py
hypnocube/cube_connector.py
hypnocube/cube_model.py
hypnocube/demo_runner.py
hypnocube/example.py
hypnocube/animations/__init__.py
hypnocube/animations/color_sorting.py
hypnocube/animations/cube_traversal.py
hypnocube/animations/random_animation.py
hypnocube/animations/season_lights.py
hypnocube-0.1.2.dist-info/DESCRIPTION.rst
hypnocube-0.1.2.dist-info/entry_points.txt
hypnocube-0.1.2.dist-info/METADATA
hypnocube-0.1.2.dist-info/metadata.json
hypnocube-0.1.2.dist-info/RECORD
hypnocube-0.1.2.dist-info/top_level.txt
hypnocube-0.1.2.dist-info/WHEEL
