Metadata-Version: 2.0
Name: hypnocube
Version: 0.1.2
Summary: Python connector for Hypnocube (www.hypnocube.com)
Home-page: https://github.com/OrigamiMarie/py_hypnocube
Author: OrigamiMarie
Author-email: origamimarie+hypnocube@gmail.com
License: MIT
Keywords: hypnocube python hypno cube
Platform: UNKNOWN
Classifier: Development Status :: 3 - Alpha
Classifier: License :: OSI Approved :: MIT License
Classifier: Programming Language :: Python :: 2
Classifier: Programming Language :: Python :: 2.6
Classifier: Programming Language :: Python :: 2.7
Requires-Dist: pyserial
Requires-Dist: crc16
